Metadata-Version: 2.1
Name: animal-script
Version: 0.8
Home-page: https://github.com/adnanattar/animal-script
Author: Adnan B. Attar
Author-email: hello@androtechbuddy.com
License: MIT
License-File: LICENSE
